README.md
setup.py
nmi/__init__.py
nmi/api.py
nmi/comm.py
nmi/payment.py
nmi_sdk.egg-info/PKG-INFO
nmi_sdk.egg-info/SOURCES.txt
nmi_sdk.egg-info/dependency_links.txt
nmi_sdk.egg-info/requires.txt
nmi_sdk.egg-info/top_level.txt
nmi_sdk.egg-info/zip-safe
tests/__init__.py
tests/test_sale.py